{
  "name": "measure_renderables",
  "parameters": [
    {
      "name": null,
      "type": "\"Console\""
    },
    {
      "name": null,
      "type": "\"ConsoleOptions\""
    },
    {
      "name": null,
      "type": "Sequence[\"RenderableType\"]"
    }
  ],
  "return_type": "\"Measurement\"",
  "docstring": null,
  "calls": [
    "max",
    "get_measurement",
    "itemgetter",
    "Measurement"
  ],
  "variables": [
    "get_measurement",
    "measurements",
    "measured_width"
  ],
  "start_line": 125,
  "end_line": 151
}